Metadata-Version: 2.1
Name: vcfsyncer
Version: 1.0.2
Summary: Package to synchronize multiple VCFs
Home-page: https://github.com/jeremy_mcrae/vcfsyncer
Author: Jeremy McRae
Author-email: jmcrae@illumina.com
License: MIT
Platform: UNKNOWN
Classifier: Development Status :: 3 - Alpha
Classifier: Topic :: Scientific/Engineering :: Bio-Informatics
